primvoices/__init__.py
primvoices/generations.py
primvoices/models.py
primvoices/voices.py
primvoices-0.1.0.dist-info/LICENSE
primvoices-0.1.0.dist-info/METADATA
primvoices-0.1.0.dist-info/WHEEL
primvoices-0.1.0.dist-info/top_level.txt
primvoices-0.1.0.dist-info/RECORD
